setup.py
iqpp/__init__.py
iqpp.plone.rating.egg-info/PKG-INFO
iqpp.plone.rating.egg-info/SOURCES.txt
iqpp.plone.rating.egg-info/dependency_links.txt
iqpp.plone.rating.egg-info/entry_points.txt
iqpp.plone.rating.egg-info/namespace_packages.txt
iqpp.plone.rating.egg-info/not-zip-safe
iqpp.plone.rating.egg-info/paster_plugins.txt
iqpp.plone.rating.egg-info/requires.txt
iqpp.plone.rating.egg-info/top_level.txt
iqpp/plone/__init__.py
iqpp/plone/rating/__init__.py
iqpp/plone/rating/config.py
iqpp/plone/rating/configure.zcml
iqpp/plone/rating/interfaces.py
iqpp/plone/rating/overrides.zcml
iqpp/plone/rating/profiles.zcml
iqpp/plone/rating/setuphandlers.py
iqpp/plone/rating/version.txt
iqpp/plone/rating/adapters/__init__.py
iqpp/plone/rating/adapters/configure.zcml
iqpp/plone/rating/adapters/manager.py
iqpp/plone/rating/adapters/options.py
iqpp/plone/rating/adapters/overrides.zcml
iqpp/plone/rating/browser/__init__.py
iqpp/plone/rating/browser/configure.zcml
iqpp/plone/rating/browser/rating.py
iqpp/plone/rating/browser/templates/__init__.py
iqpp/plone/rating/browser/templates/configure.zcml
iqpp/plone/rating/browser/templates/object_ratings.pt
iqpp/plone/rating/browser/templates/object_ratings.py
iqpp/plone/rating/browser/templates/options_tab.py
iqpp/plone/rating/browser/templates/rated_objects.pt
iqpp/plone/rating/browser/templates/rated_objects.py
iqpp/plone/rating/browser/templates/rating_folder_listing.py
iqpp/plone/rating/controlpanel/__init__.py
iqpp/plone/rating/controlpanel/rating.py
iqpp/plone/rating/kss/__init__.py
iqpp/plone/rating/kss/configure.zcml
iqpp/plone/rating/kss/rating.kss
iqpp/plone/rating/kss/rating.py
iqpp/plone/rating/portlets/__init__.py
iqpp/plone/rating/portlets/configure.zcml
iqpp/plone/rating/portlets/most_active.pt
iqpp/plone/rating/portlets/most_active.py
iqpp/plone/rating/portlets/rating.pt
iqpp/plone/rating/portlets/rating.py
iqpp/plone/rating/profiles/default/actions.xml
iqpp/plone/rating/profiles/default/controlpanel.xml
iqpp/plone/rating/profiles/default/import_steps.xml
iqpp/plone/rating/profiles/default/kssregistry.xml
iqpp/plone/rating/profiles/default/portlets.xml
iqpp/plone/rating/profiles/default/skins.xml
iqpp/plone/rating/profiles/default/types.xml
iqpp/plone/rating/profiles/default/viewlets.xml
iqpp/plone/rating/profiles/default/types/Folder.xml
iqpp/plone/rating/profiles/default/types/Topic.xml
