Metadata-Version: 1.0
Name: iqpp.plone.rating
Version: 2.0-rc1
Summary: Enables rating for Plone's default content types.
Home-page: http://iqpp.de
Author: Kai Diefenbach
Author-email: kai.diefenbach@iqpp.de
License: GPL
Platform: UNKNOWN
Classifier: Framework :: Plone
Classifier: Framework :: Zope2
Classifier: Framework :: Zope3
Classifier: Programming Language :: Python
Classifier: Topic :: Software Development :: Libraries :: Python Modules
